{
  "config": {
    "abort": {
      "already_configured": "[%key:common::config_flow::abort::already_configured_device%]"
    },
    "error": {
      "cannot_connect": "[%key:common::config_flow::error::cannot_connect%]"
    },
    "step": {
      "user": {
        "data": {
          "id": "Installation",
          "username": "[%key:common::config_flow::data::username%]",
          "password": "[%key:common::config_flow::data::password%]"
        }
      }
    }
  },
  "entity": {
    "binary_sensor": {
      "air_demand": {
        "name": "Air demand"
      },
      "air_quality_active": {
        "name": "Air Quality active"
      },
      "floor_demand": {
        "name": "Floor demand"
      }
    },
    "select": {
      "air_quality": {
        "name": "Air Quality mode",
        "state": {
          "off": "Off",
          "on": "On",
          "auto": "Auto"
        }
      }
    },
    "sensor": {
      "cpu_usage": {
        "name": "CPU usage"
      },
      "free_memory": {
        "name": "Free memory"
      },
      "thermostat_coverage": {
        "name": "Signal percentage"
      }
    }
  }
}
