{
    "config": {
        "abort": {
            "host_port_exists": "Deze combinatie van host en poort is al geconfigureerd"
        },
        "error": {
            "certificate_error": "Certificaat kon niet worden gevalideerd",
            "certificate_fetch_failed": "Kan certificaat niet ophalen van deze combinatie van host en poort",
            "connection_timeout": "Time-out bij verbinding maken met deze host",
            "host_port_exists": "Deze combinatie van host en poort is al geconfigureerd",
            "resolve_failed": "Deze host kon niet gevonden worden",
            "wrong_host": "Certificaat komt niet overeen met hostnaam"
        },
        "step": {
            "user": {
                "data": {
                    "host": "De hostnaam van het certificaat",
                    "name": "De naam van het certificaat",
                    "port": "De poort van het certificaat"
                },
                "title": "Het certificaat defini\u00ebren dat moet worden getest"
            }
        },
        "title": "Vervaldatum certificaat"
    }
}