{
  "config": {
    "abort": {
      "already_configured": "[%key:common::config_flow::abort::already_configured_device%]",
      "no_devices_found": "[%key:common::config_flow::abort::no_devices_found%]"
    },
    "error": {
      "cannot_connect": "[%key:common::config_flow::error::cannot_connect%]"
    },
    "step": {
      "user": {
        "menu_options": {
          "discovery": "Scan the network for devices",
          "manual": "Enter IP address manually"
        }
      },
      "discovery": {
        "description": "[%key:common::config_flow::description::confirm_setup%]"
      },
      "manual": {
        "data": {
          "ip_address": "IP address"
        }
      }
    }
  },
  "entity": {
    "switch": {
      "fresh_air": {
        "name": "Fresh air"
      },
      "health_mode": {
        "name": "Health mode"
      },
      "light": {
        "name": "Panel light"
      },
      "quiet": {
        "name": "Quiet mode"
      },
      "xfan": {
        "name": "Xtra fan"
      }
    }
  }
}
