{
  "config": {
    "abort": {
      "already_configured": "\uae30\uae30\uac00 \uc774\ubbf8 \uad6c\uc131\ub418\uc5c8\uc2b5\ub2c8\ub2e4"
    },
    "error": {
      "cannot_connect": "\uc5f0\uacb0 \uc624\ub958\uac00 \ubc1c\uc0dd\ud588\uc2b5\ub2c8\ub2e4",
      "invalid_auth": "\uc778\uc99d\uc774 \uc798\ubabb\ub418\uc5c8\uc2b5\ub2c8\ub2e4",
      "unknown": "\uc608\uc0c1\uce58 \ubabb\ud55c \uc624\ub958\uac00 \ubc1c\uc0dd\ud588\uc2b5\ub2c8\ub2e4"
    },
    "step": {
      "user": {
        "data": {
          "password": "\ube44\ubc00\ubc88\ud638",
          "username": "\uc0ac\uc6a9\uc790 \uc774\ub984"
        },
        "title": "Carson \uacc4\uc815\uc73c\ub85c \ub85c\uadf8\uc778"
      }
    },
    "title": "Carson"
  },
  "options": {
    "step": {
      "carson_devices": {
        "description": "Carson \uae30\uae30 \uc720\ud615\uc758 \ud45c\uc2dc \uc5ec\ubd80 \uad6c\uc131",
        "data": {
          "list_from_eagle_eye": "Eagle Eye \uc5d0\uc11c \uc9c1\uc811 \uce74\uba54\ub77c \ubaa9\ub85d"
        }
      }
    }
  }
}