{
  "config": {
    "abort": {
      "already_configured": "[%key:common::config_flow::abort::already_configured_device%]",
      "reauth_successful": "[%key:common::config_flow::abort::reauth_successful%]"
    },
    "error": {
      "cannot_connect": "[%key:common::config_flow::error::cannot_connect%]",
      "invalid_auth": "[%key:common::config_flow::error::invalid_auth%]",
      "pairing_failed": "Pairing failed; please check the Bosch Smart Home Controller is in pairing mode (LED flashing) as well as your password is correct.",
      "session_error": "Session error: API returned Non-OK result.",
      "unknown": "[%key:common::config_flow::error::unknown%]"
    },
    "flow_title": "Bosch SHC: {name}",
    "step": {
      "confirm_discovery": {
        "description": "Smart Home Controller I: Please press the front-side button until LED starts flashing.\nSmart Home Controller II: Press the function button shortly. Cloud and network lights start blinking orange.\nDevice is now ready to be paired.\n\nReady to continue to set up {model} @ {host} with Home Assistant?"
      },
      "credentials": {
        "data": {
          "password": "[%key:common::config_flow::data::password%]"
        },
        "data_description": {
          "password": "Password of the Smart Home Controller"
        }
      },
      "reauth_confirm": {
        "data": {
          "host": "[%key:common::config_flow::data::host%]"
        },
        "description": "The Bosch SHC integration needs to re-authenticate your account",
        "title": "[%key:common::config_flow::title::reauth%]"
      },
      "user": {
        "data": {
          "host": "[%key:common::config_flow::data::host%]"
        },
        "data_description": {
          "host": "The hostname or IP address of your Bosch Smart Home Controller."
        },
        "description": "Set up your Bosch Smart Home Controller to allow monitoring and control with Home Assistant.",
        "title": "SHC authentication parameters"
      }
    }
  },
  "entity": {
    "select": {
      "actuator_type": {
        "name": "Actuator type",
        "state": {
          "normally_closed": "Normally closed",
          "normally_open": "Normally open",
          "unsupported": "Unsupported"
        }
      },
      "display_direction": {
        "name": "Display direction",
        "state": {
          "normal": "[%key:common::state::normal%]",
          "reversed": "Reversed"
        }
      },
      "displayed_temperature": {
        "name": "Displayed temperature",
        "state": {
          "measured": "Measured",
          "setpoint": "Setpoint"
        }
      },
      "heater_type": {
        "name": "Heater type",
        "state": {
          "convector_active": "Convector (active)",
          "convector_passive": "Convector (passive)",
          "floor_heating": "Floor heating",
          "floor_heating_low_energy": "Floor heating (low energy)",
          "radiator": "Radiator"
        }
      },
      "motion_sensitivity": {
        "name": "Motion sensitivity",
        "state": {
          "high": "[%key:common::state::high%]",
          "low": "[%key:common::state::low%]",
          "middle": "Middle"
        }
      },
      "orientation_light_response": {
        "name": "Orientation light response time",
        "state": {
          "long": "Long",
          "short": "Short"
        }
      },
      "output_mode": {
        "name": "Output mode",
        "state": {
          "attached": "Attached",
          "detached": "Detached",
          "detached_long_press": "Detached (long press)",
          "detached_short_press": "Detached (short press)",
          "unsupported": "[%key:component::bosch_shc::entity::select::actuator_type::state::unsupported%]"
        }
      },
      "smart_sensitivity_comfort": {
        "name": "Comfort sensitivity level",
        "state": {
          "high": "[%key:common::state::high%]",
          "low": "[%key:common::state::low%]",
          "middle": "[%key:component::bosch_shc::entity::select::motion_sensitivity::state::middle%]"
        }
      },
      "smart_sensitivity_security": {
        "name": "Security sensitivity level",
        "state": {
          "high": "[%key:common::state::high%]",
          "low": "[%key:common::state::low%]",
          "middle": "[%key:component::bosch_shc::entity::select::motion_sensitivity::state::middle%]"
        }
      },
      "smoke_sensitivity": {
        "name": "Smoke sensitivity",
        "state": {
          "high": "[%key:common::state::high%]",
          "low": "[%key:common::state::low%]",
          "middle": "[%key:component::bosch_shc::entity::select::motion_sensitivity::state::middle%]"
        }
      },
      "state_after_power_outage": {
        "name": "State after power outage",
        "state": {
          "last_state": "Last state",
          "off": "[%key:common::state::off%]",
          "on": "[%key:common::state::on%]"
        }
      },
      "switch_type": {
        "name": "Switch type",
        "state": {
          "no_switch": "No switch",
          "none": "None",
          "pushbutton": "Pushbutton",
          "switch": "Switch"
        }
      },
      "terminal_type": {
        "name": "Terminal type",
        "state": {
          "floor_sensor_connected": "Floor sensor connected",
          "floor_sensor_displayed": "Floor sensor displayed",
          "floor_sensor_displayed_and_used_for_regulation": "Floor sensor displayed and used for regulation",
          "floor_sensor_used_for_regulation": "Floor sensor used for regulation",
          "not_connected": "Not connected",
          "outdoor_sensor_connected": "Outdoor sensor connected",
          "volt_free_sensor_connected": "Volt-free sensor connected",
          "volt_free_sensor_connected_and_used_for_operation": "Volt-free sensor connected and used for operation"
        }
      },
      "valve_type": {
        "name": "Valve type",
        "state": {
          "normally_close": "[%key:component::bosch_shc::entity::select::actuator_type::state::normally_closed%]",
          "normally_open": "[%key:component::bosch_shc::entity::select::actuator_type::state::normally_open%]"
        }
      },
      "vibration_sensitivity": {
        "name": "Vibration sensitivity",
        "state": {
          "high": "[%key:common::state::high%]",
          "low": "[%key:common::state::low%]",
          "medium": "[%key:common::state::medium%]",
          "very_high": "[%key:common::state::very_high%]",
          "very_low": "[%key:common::state::very_low%]"
        }
      }
    },
    "sensor": {
      "air_quality": {
        "name": "Air quality"
      },
      "communication_quality": {
        "name": "Communication quality"
      },
      "humidity_rating": {
        "name": "Humidity rating"
      },
      "purity": {
        "name": "Purity"
      },
      "purity_rating": {
        "name": "Purity rating"
      },
      "temperature_rating": {
        "name": "Temperature rating"
      },
      "valvetappet": {
        "name": "Valvetappet"
      }
    },
    "switch": {
      "routing": {
        "name": "Routing"
      }
    }
  }
}
