{
    "config": {
        "abort": {
            "already_configured": "Urz\u0105dzenie jest ju\u017c skonfigurowane."
        },
        "error": {
            "already_configured": "Urz\u0105dzenie jest ju\u017c skonfigurowane.",
            "cannot_connect": "Nie mo\u017cna nawi\u0105za\u0107 po\u0142\u0105czenia, sprawd\u017a adres hosta"
        },
        "step": {
            "user": {
                "data": {
                    "host": "Nazwa hosta lub adres IP urz\u0105dzenia Solar-Log",
                    "name": "Prefiks dla sensor\u00f3w Solar-Log"
                },
                "title": "Zdefiniuj po\u0142\u0105czenie z Solar-Log"
            }
        }
    }
}