{
  "config": {
    "step": {
      "user": {
        "data": {
          "app_key": "Application Key"
        },
        "title": "Authentication",
        "description": "Enter your TfL Application Key"
      },
      "stop_point": {
        "data": {
          "stop_point": "Stop Point",
          "add_another": "Add another stop point?"
        },
        "title": "Stop Points",
        "description": "Add your Stop Points"
      }
    },
    "error": {
      "cannot_connect": "[%key:common::config_flow::error::cannot_connect%]",
      "invalid_auth": "[%key:common::config_flow::error::invalid_auth%]",
      "unknown": "[%key:common::config_flow::error::unknown%]",
      "invalid_stop_point": "The Stop Point {stop_point} is invalid"
    },
    "abort": {
      "already_configured": "[%key:common::config_flow::abort::already_configured_device%]"
    }
  },
  "options": {
    "step": {
      "init": {
        "title": "Edit Configuration",
        "description": "Update API Key and Stop Points",
        "data": {
          "app_key": "Application Key",
          "stop_points": "Stop Points",
          "stop_point": "Add Stop Point"
        }
      }
    },
    "error": {
      "invalid_auth": "[%key:common::config_flow::error::invalid_auth%]",
      "cannot_connect": "[%key:common::config_flow::error::cannot_connect%]",
      "unknown": "[%key:common::config_flow::error::unknown%]",
      "invalid_stop_point": "The Stop Point {stop_point} is invalid"
    }
  }
}
