{
    "config": {
        "title": "AIS SUPLA",
        "step": {
            "init": {
                "title": "Podaj parametry połączenia z serwerem Supla",
                "description": "Wykryjemy Twoje urządzenia na serwerze Supla Cloud lub na Twoim serwerze Supla.\n\n {error_info} ",
                "data": {
                     "server": "Serwer",
                     "access_token": "Token"
                }
            },
           "confirm": {
                "description": "![Supla logo](/static/icons/supla_zamel_logo.png)\n\nCzy chcesz połączyć się z serwerem Supla by wykryć swoje urządzenia?",
                "title": "Połączenie z Supla Cloud"
           }
        },
        "error": {
            "supla_no_connection": "Nie można połączyć z Supla Cloud"
        }
    }
}